govplanet/__init__.py
govplanet/govplanet_api.py
govplanet_api-1.0.0.dist-info/licenses/LICENSE
govplanet_api-1.0.0.dist-info/METADATA
govplanet_api-1.0.0.dist-info/WHEEL
govplanet_api-1.0.0.dist-info/top_level.txt
govplanet_api-1.0.0.dist-info/RECORD
