Metadata-Version: 2.4
Name: govplanet-api
Version: 1.0.0
Summary: A complete reverse-engineered API client for GovPlanet with extensive product search capabilities
Home-page: https://github.com/yourusername/govplanet-api
Author: Jonathan Gan
Author-email: Jonathan Gan <jonny2298@live.com>
License-Expression: MIT
Project-URL: Homepage, https://github.com/yourusername/govplanet-api
Project-URL: Documentation, https://github.com/yourusername/govplanet-api#readme
Project-URL: Repository, https://github.com/yourusername/govplanet-api
Project-URL: Issues, https://github.com/yourusername/govplanet-api/issues
Keywords: govplanet,api,client,search,products,auction
Classifier: Development Status :: 4 - Beta
Classifier: Intended Audience :: Developers
Classifier: Topic :: Software Development :: Libraries :: Python Modules
Classifier: Programming Language :: Python :: 3
Classifier: Programming Language :: Python :: 3.8
Classifier: Programming Language :: Python :: 3.9
Classifier: Programming Language :: Python :: 3.10
Classifier: Programming Language :: Python :: 3.11
Classifier: Programming Language :: Python :: 3.12
Requires-Python: >=3.8
License-File: LICENSE
Requires-Dist: requests>=2.31.0
Provides-Extra: dev
Requires-Dist: pytest>=7.0.0; extra == "dev"
Requires-Dist: black>=23.0.0; extra == "dev"
Requires-Dist: flake8>=6.0.0; extra == "dev"
Dynamic: author
Dynamic: home-page
Dynamic: license-file
Dynamic: requires-python
